dellemc_unity_sdk/__init__.py
dellemc_unity_sdk/constants.py
dellemc_unity_sdk/rest_supported_enums.py
dellemc_unity_sdk/runner.py
dellemc_unity_sdk/supportive_functions.py
dellemc_unity_sdk/unity.py
dellemc_unity_sdk/validator.py
dellemc_unity_sdk-1.0.dist-info/DESCRIPTION.rst
dellemc_unity_sdk-1.0.dist-info/METADATA
dellemc_unity_sdk-1.0.dist-info/RECORD
dellemc_unity_sdk-1.0.dist-info/WHEEL
dellemc_unity_sdk-1.0.dist-info/metadata.json
dellemc_unity_sdk-1.0.dist-info/top_level.txt
