Metadata-Version: 2.0
Name: dellemc-unity-sdk
Version: 1.0
Summary: Package used to create requests to DellEMC Unity.
Home-page: https://github.com/ansible-dellemc-unity/dellemc-unity-sdk
Author: ansible-dellemc-unity
Author-email: mityushin.dmitry@gmail.com
License: UNKNOWN
Platform: UNKNOWN
Classifier: Programming Language :: Python
Classifier: License :: OSI Approved :: MIT License
Classifier: Operating System :: OS Independent
Requires-Dist: dellemc-unity-sdk
